{
  "id": "persona-096",
  "name": "Aisha",
  "ageBand": "senior",
  "sex": "unspecified",
  "industry": "manufacturing",
  "domain": "community",
  "roleFamily": "creator",
  "regionGroup": "north_america",
  "techFamiliarity": "medium",
  "spendingStyle": "premium_sensitive",
  "decisionStyle": "risk_averse",
  "skepticismLevel": "high",
  "toneBaseline": "blunt",
  "archetype": "family-centered decision maker",
  "lifeStage": "community_volunteer",
  "summary": "Aisha is a community volunteer in manufacturing — family-centered decision maker with a blunt baseline and risk averse decision-making.",
  "tags": [
    "manufacturing",
    "senior",
    "creator",
    "community"
  ]
}
