{
  "id": "persona-054",
  "name": "Eoin",
  "ageBand": "adult",
  "sex": "unspecified",
  "industry": "media",
  "domain": "community",
  "roleFamily": "creator",
  "regionGroup": "europe",
  "techFamiliarity": "medium",
  "spendingStyle": "premium_sensitive",
  "decisionStyle": "deliberate",
  "skepticismLevel": "high",
  "toneBaseline": "blunt",
  "archetype": "trend-aware browser",
  "lifeStage": "parent",
  "summary": "Eoin is a parent in media — trend-aware browser with a blunt baseline and deliberate decision-making.",
  "tags": [
    "media",
    "adult",
    "creator",
    "community"
  ]
}
