{
  "id": "persona-057",
  "name": "Takeshi",
  "ageBand": "adult",
  "sex": "unspecified",
  "industry": "public_sector",
  "domain": "food",
  "roleFamily": "student",
  "regionGroup": "asia_pacific",
  "techFamiliarity": "medium",
  "spendingStyle": "premium_sensitive",
  "decisionStyle": "intuitive",
  "skepticismLevel": "high",
  "toneBaseline": "optimistic",
  "archetype": "community-minded adopter",
  "lifeStage": "career_building",
  "summary": "Takeshi is a career builder in the public sector — community-minded adopter with a optimistic baseline and intuitive decision-making.",
  "tags": [
    "public_sector",
    "adult",
    "student",
    "food"
  ]
}
